pydot_ng/__init__.py
pydot_ng/_dotparser.py
pydot_ng-2.0.0.dist-info/LICENSE
pydot_ng-2.0.0.dist-info/METADATA
pydot_ng-2.0.0.dist-info/WHEEL
pydot_ng-2.0.0.dist-info/top_level.txt
pydot_ng-2.0.0.dist-info/RECORD
