Metadata-Version: 1.2
Name: pydot-ng
Version: 2.0.0
Summary: Python interface to Graphviz's Dot
Home-page: https://github.com/pydot/pydot-ng
Author: Ero Carrera
Author-email: ero@dkbza.org
Maintainer: Sebastian Kalinowski
Maintainer-email: sebastian@kalinowski.eu
License: MIT
Keywords: graphviz dot graphs visualization
Platform: any
Classifier: Development Status :: 5 - Production/Stable
Classifier: Intended Audience :: Science/Research
Classifier: License :: OSI Approved :: MIT License
Classifier: Natural Language :: English
Classifier: Operating System :: OS Independent
Classifier: Programming Language :: Python :: 2.7
Classifier: Programming Language :: Python :: 3.4
Classifier: Programming Language :: Python :: 3.5
Classifier: Programming Language :: Python :: 3.6
Classifier: Programming Language :: Python :: 3.7
Classifier: Programming Language :: Python
Classifier: Topic :: Scientific/Engineering :: Visualization
Classifier: Topic :: Software Development :: Libraries :: Python Modules
